{"cameraMode":{"drawMode":0,"name":"Shaded","section":"Shading Mode"},"sceneLighting":true,"audioPlay":false,"sceneViewState":{"m_AlwaysRefresh":false,"showFog":true,"showSkybox":true,"showFlares":true,"showImageEffects":true,"showParticleSystems":true,"showVisualEffectGraphs":true,"m_FxEnabled":true},"in2DMode":false,"pivot":{"x":-0.09211434423923493,"y":0.7484198808670044,"z":-0.3337154686450958},"rotation":{"x":-0.1427440047264099,"y":0.7944226861000061,"z":-0.2048082798719406,"w":-0.553703248500824},"size":1.422731637954712,"orthographic":false}